python_bundler/__init__.py
python_bundler/__main__.py
python_bundler/compile.py
python_bundler/main_template.py
python_bundler-0.3.0.dist-info/LICENSE
python_bundler-0.3.0.dist-info/METADATA
python_bundler-0.3.0.dist-info/WHEEL
python_bundler-0.3.0.dist-info/entry_points.txt
python_bundler-0.3.0.dist-info/RECORD
