Metadata-Version: 2.3
Name: python-bundler
Version: 0.3.0
Summary: 
Author: Zach Taira
Author-email: zach.taira@gmail.com
Requires-Python: >=3.9, <4.0.0
Classifier: Programming Language :: Python :: 3
Classifier: Programming Language :: Python :: 3.9
Classifier: Programming Language :: Python :: 3.10
Classifier: Programming Language :: Python :: 3.11
Classifier: Programming Language :: Python :: 3.12
Classifier: Programming Language :: Python :: 3.13
Requires-Dist: poetry (>=2.0.1,<3.0.0)
